Workbook

Sheet Summary
A1: Jobab
A2: AI shop assistant for Bangladeshi merchants
A3: Pre-seed financial model · 36 months · all USD
A5: AT A GLANCE
A7: Target raise | B7: $400,000
A8: Months runway | B8: 18
A9: Merchants by EOY1 | B9: 100
A10: MRR by EOY1 | B10: $1,700
A11: Merchants by EOY2 | B11: 500
A12: MRR by EOY2 | B12: $14,000
A13: Merchants by EOY3 | B13: 1,200
A14: MRR by EOY3 | B14: $33,600
A15: Cash-flow positive | B15: Month 24
A16: LTV : CAC target | B16: 17 : 1
A17: Gross margin (Growth tier) | B17: ~85%
A20: SHEETS IN THIS WORKBOOK
A22: Assumptions | B22: Tweak any number — P&L recalculates
A23: Monthly P&L | B23: 36-month revenue + cost projection
A24: Charts | B24: MRR / merchants / burn visualisations
A25: Use of funds | B25: Where the $400K goes

Sheet Assumptions
A1: Jobab — financial model assumptions
A2: All revenue numbers in USD. 1 USD ≈ ৳110. Tweak any cell — P&L recalculates.
A4: PRICING & MIX
A5: Starter price (USD/mo) | B5: 9 | C5: ৳999
A6: Growth price (USD/mo) | B6: 27 | C6: ৳2,999
A7: Pro price (USD/mo) | B7: 73 | C7: ৳7,999
A8: Plan mix — Starter (Y1) | B8: 0.6 | C8: %
A9: Plan mix — Growth (Y1) | B9: 0.3 | C9: %
A10: Plan mix — Pro (Y1) | B10: 0.1 | C10: %
A11: Plan mix — Starter (Y2+) | B11: 0.4 | C11: %
A12: Plan mix — Growth (Y2+) | B12: 0.45 | C12: %
A13: Plan mix — Pro (Y2+) | B13: 0.15 | C13: %
A15: UNIT ECONOMICS
A16: COGS per conversation (USD) | B16: 0.003 | C16: Groq + vision + embeddings
A17: Conversations per merchant/mo | B17: 1500 | C17: Average
A18: Fixed infra cost (USD/mo) | B18: 100 | C18: Hosting + DB + Redis
A19: Monthly logo churn | B19: 0.04 | C19: 4% — SMB SaaS norm in EM
A21: ACQUISITION
A22: CAC (USD) | B22: 32 | C22: ৳3,500
A23: Trial → paid conversion | B23: 0.4 | C23: 40% activation
A24: Average merchant lifetime (months) | B24: 25 | C24: =1 / churn
A26: HIRING (USD/mo cost)
A27: Founder | B27: 1360 | C27: M1+
A28: Senior engineer | B28: 1820 | C28: M4+
A29: Merchant ops | B29: 730 | C29: M6+
A30: Fractional CFO | B30: 545 | C30: M12+
A31: Second engineer | B31: 1635 | C31: M18+
A32: BD lead | B32: 1090 | C32: M24+
A34: OTHER OPEX
A35: Marketing — early (USD/mo) | B35: 500 | C35: M1–M12
A36: Marketing — late (USD/mo) | B36: 2000 | C36: M13+
A37: Legal + accounting (USD/mo) | B37: 200
A38: Software (USD/mo) | B38: 100
A39: Office (USD/mo) | B39: 300

Sheet Monthly P&L
A1: Monthly P&L — 36-month projection (USD)
A3: Month | B3: Merchants (end) | C3: Blended ARPU | D3: MRR | E3: COGS | F3: Gross profit | G3: Salaries | H3: Marketing | I3: Infra | J3: Other OpEx | K3: Total OpEx | L3: Net (burn) | M3: Cumulative burn | N3: ARR
A4: M1 | B4: 0 | C4: =Assumptions!$B$5*Assumptions!$B$8+Assumptions!$B$6*Assumptions!$B$9+Assumptions!$B$7*Assumptions!$B$10 | D4: =B4*C4 | E4: =B4*Assumptions!$B$18*Assumptions!$B$17 | F4: =D4-E4 | G4: =Assumptions!$B$28 | H4: =Assumptions!$B$36 | I4: =Assumptions!$B$19+IF(B4>500,B4*0.4,0) | J4: =Assumptions!$B$38+Assumptions!$B$39+Assumptions!$B$40 | K4: =G4+H4+I4+J4 | L4: =F4-K4 | M4: =L4 | N4: =D4*12
A5: M2 | B5: 0 | C5: =Assumptions!$B$5*Assumptions!$B$8+Assumptions!$B$6*Assumptions!$B$9+Assumptions!$B$7*Assumptions!$B$10 | D5: =B5*C5 | E5: =B5*Assumptions!$B$18*Assumptions!$B$17 | F5: =D5-E5 | G5: =Assumptions!$B$28 | H5: =Assumptions!$B$36 | I5: =Assumptions!$B$19+IF(B5>500,B5*0.4,0) | J5: =Assumptions!$B$38+Assumptions!$B$39+Assumptions!$B$40 | K5: =G5+H5+I5+J5 | L5: =F5-K5 | M5: =M4+L5 | N5: =D5*12
A6: M3 | B6: 0 | C6: =Assumptions!$B$5*Assumptions!$B$8+Assumptions!$B$6*Assumptions!$B$9+Assumptions!$B$7*Assumptions!$B$10 | D6: =B6*C6 | E6: =B6*Assumptions!$B$18*Assumptions!$B$17 | F6: =D6-E6 | G6: =Assumptions!$B$28 | H6: =Assumptions!$B$36 | I6: =Assumptions!$B$19+IF(B6>500,B6*0.4,0) | J6: =Assumptions!$B$38+Assumptions!$B$39+Assumptions!$B$40 | K6: =G6+H6+I6+J6 | L6: =F6-K6 | M6: =M5+L6 | N6: =D6*12
A7: M4 | B7: 8 | C7: =Assumptions!$B$5*Assumptions!$B$8+Assumptions!$B$6*Assumptions!$B$9+Assumptions!$B$7*Assumptions!$B$10 | D7: =B7*C7 | E7: =B7*Assumptions!$B$18*Assumptions!$B$17 | F7: =D7-E7 | G7: =Assumptions!$B$28+Assumptions!$B$29 | H7: =Assumptions!$B$36 | I7: =Assumptions!$B$19+IF(B7>500,B7*0.4,0) | J7: =Assumptions!$B$38+Assumptions!$B$39+Assumptions!$B$40 | K7: =G7+H7+I7+J7 | L7: =F7-K7 | M7: =M6+L7 | N7: =D7*12
A8: M5 | B8: 15 | C8: =Assumptions!$B$5*Assumptions!$B$8+Assumptions!$B$6*Assumptions!$B$9+Assumptions!$B$7*Assumptions!$B$10 | D8: =B8*C8 | E8: =B8*Assumptions!$B$18*Assumptions!$B$17 | F8: =D8-E8 | G8: =Assumptions!$B$28+Assumptions!$B$29 | H8: =Assumptions!$B$36 | I8: =Assumptions!$B$19+IF(B8>500,B8*0.4,0) | J8: =Assumptions!$B$38+Assumptions!$B$39+Assumptions!$B$40 | K8: =G8+H8+I8+J8 | L8: =F8-K8 | M8: =M7+L8 | N8: =D8*12
A9: M6 | B9: 25 | C9: =Assumptions!$B$5*Assumptions!$B$8+Assumptions!$B$6*Assumptions!$B$9+Assumptions!$B$7*Assumptions!$B$10 | D9: =B9*C9 | E9: =B9*Assumptions!$B$18*Assumptions!$B$17 | F9: =D9-E9 | G9: =Assumptions!$B$28+Assumptions!$B$29+Assumptions!$B$30 | H9: =Assumptions!$B$36 | I9: =Assumptions!$B$19+IF(B9>500,B9*0.4,0) | J9: =Assumptions!$B$38+Assumptions!$B$39+Assumptions!$B$40 | K9: =G9+H9+I9+J9 | L9: =F9-K9 | M9: =M8+L9 | N9: =D9*12
A10: M7 | B10: 38 | C10: =Assumptions!$B$5*Assumptions!$B$8+Assumptions!$B$6*Assumptions!$B$9+Assumptions!$B$7*Assumptions!$B$10 | D10: =B10*C10 | E10: =B10*Assumptions!$B$18*Assumptions!$B$17 | F10: =D10-E10 | G10: =Assumptions!$B$28+Assumptions!$B$29+Assumptions!$B$30 | H10: =Assumptions!$B$36 | I10: =Assumptions!$B$19+IF(B10>500,B10*0.4,0) | J10: =Assumptions!$B$38+Assumptions!$B$39+Assumptions!$B$40 | K10: =G10+H10+I10+J10 | L10: =F10-K10 | M10: =M9+L10 | N10: =D10*12
A11: M8 | B11: 48 | C11: =Assumptions!$B$5*Assumptions!$B$8+Assumptions!$B$6*Assumptions!$B$9+Assumptions!$B$7*Assumptions!$B$10 | D11: =B11*C11 | E11: =B11*Assumptions!$B$18*Assumptions!$B$17 | F11: =D11-E11 | G11: =Assumptions!$B$28+Assumptions!$B$29+Assumptions!$B$30 | H11: =Assumptions!$B$36 | I11: =Assumptions!$B$19+IF(B11>500,B11*0.4,0) | J11: =Assumptions!$B$38+Assumptions!$B$39+Assumptions!$B$40 | K11: =G11+H11+I11+J11 | L11: =F11-K11 | M11: =M10+L11 | N11: =D11*12
A12: M9 | B12: 60 | C12: =Assumptions!$B$5*Assumptions!$B$8+Assumptions!$B$6*Assumptions!$B$9+Assumptions!$B$7*Assumptions!$B$10 | D12: =B12*C12 | E12: =B12*Assumptions!$B$18*Assumptions!$B$17 | F12: =D12-E12 | G12: =Assumptions!$B$28+Assumptions!$B$29+Assumptions!$B$30 | H12: =Assumptions!$B$36 | I12: =Assumptions!$B$19+IF(B12>500,B12*0.4,0) | J12: =Assumptions!$B$38+Assumptions!$B$39+Assumptions!$B$40 | K12: =G12+H12+I12+J12 | L12: =F12-K12 | M12: =M11+L12 | N12: =D12*12
A13: M10 | B13: 72 | C13: =Assumptions!$B$5*Assumptions!$B$8+Assumptions!$B$6*Assumptions!$B$9+Assumptions!$B$7*Assumptions!$B$10 | D13: =B13*C13 | E13: =B13*Assumptions!$B$18*Assumptions!$B$17 | F13: =D13-E13 | G13: =Assumptions!$B$28+Assumptions!$B$29+Assumptions!$B$30 | H13: =Assumptions!$B$36 | I13: =Assumptions!$B$19+IF(B13>500,B13*0.4,0) | J13: =Assumptions!$B$38+Assumptions!$B$39+Assumptions!$B$40 | K13: =G13+H13+I13+J13 | L13: =F13-K13 | M13: =M12+L13 | N13: =D13*12
A14: M11 | B14: 86 | C14: =Assumptions!$B$5*Assumptions!$B$8+Assumptions!$B$6*Assumptions!$B$9+Assumptions!$B$7*Assumptions!$B$10 | D14: =B14*C14 | E14: =B14*Assumptions!$B$18*Assumptions!$B$17 | F14: =D14-E14 | G14: =Assumptions!$B$28+Assumptions!$B$29+Assumptions!$B$30 | H14: =Assumptions!$B$36 | I14: =Assumptions!$B$19+IF(B14>500,B14*0.4,0) | J14: =Assumptions!$B$38+Assumptions!$B$39+Assumptions!$B$40 | K14: =G14+H14+I14+J14 | L14: =F14-K14 | M14: =M13+L14 | N14: =D14*12
A15: M12 | B15: 100 | C15: =Assumptions!$B$5*Assumptions!$B$8+Assumptions!$B$6*Assumptions!$B$9+Assumptions!$B$7*Assumptions!$B$10 | D15: =B15*C15 | E15: =B15*Assumptions!$B$18*Assumptions!$B$17 | F15: =D15-E15 | G15: =Assumptions!$B$28+Assumptions!$B$29+Assumptions!$B$30+Assumptions!$B$31 | H15: =Assumptions!$B$36 | I15: =Assumptions!$B$19+IF(B15>500,B15*0.4,0) | J15: =Assumptions!$B$38+Assumptions!$B$39+Assumptions!$B$40 | K15: =G15+H15+I15+J15 | L15: =F15-K15 | M15: =M14+L15 | N15: =D15*12
A16: M13 | B16: 118 | C16: =Assumptions!$B$5*Assumptions!$B$11+Assumptions!$B$6*Assumptions!$B$12+Assumptions!$B$7*Assumptions!$B$13 | D16: =B16*C16 | E16: =B16*Assumptions!$B$18*Assumptions!$B$17 | F16: =D16-E16 | G16: =Assumptions!$B$28+Assumptions!$B$29+Assumptions!$B$30+Assumptions!$B$31 | H16: =Assumptions!$B$37 | I16: =Assumptions!$B$19+IF(B16>500,B16*0.4,0) | J16: =Assumptions!$B$38+Assumptions!$B$39+Assumptions!$B$40 | K16: =G16+H16+I16+J16 | L16: =F16-K16 | M16: =M15+L16 | N16: =D16*12
A17: M14 | B17: 138 | C17: =Assumptions!$B$5*Assumptions!$B$11+Assumptions!$B$6*Assumptions!$B$12+Assumptions!$B$7*Assumptions!$B$13 | D17: =B17*C17 | E17: =B17*Assumptions!$B$18*Assumptions!$B$17 | F17: =D17-E17 | G17: =Assumptions!$B$28+Assumptions!$B$29+Assumptions!$B$30+Assumptions!$B$31 | H17: =Assumptions!$B$37 | I17: =Assumptions!$B$19+IF(B17>500,B17*0.4,0) | J17: =Assumptions!$B$38+Assumptions!$B$39+Assumptions!$B$40 | K17: =G17+H17+I17+J17 | L17: =F17-K17 | M17: =M16+L17 | N17: =D17*12
A18: M15 | B18: 160 | C18: =Assumptions!$B$5*Assumptions!$B$11+Assumptions!$B$6*Assumptions!$B$12+Assumptions!$B$7*Assumptions!$B$13 | D18: =B18*C18 | E18: =B18*Assumptions!$B$18*Assumptions!$B$17 | F18: =D18-E18 | G18: =Assumptions!$B$28+Assumptions!$B$29+Assumptions!$B$30+Assumptions!$B$31 | H18: =Assumptions!$B$37 | I18: =Assumptions!$B$19+IF(B18>500,B18*0.4,0) | J18: =Assumptions!$B$38+Assumptions!$B$39+Assumptions!$B$40 | K18: =G18+H18+I18+J18 | L18: =F18-K18 | M18: =M17+L18 | N18: =D18*12
A19: M16 | B19: 184 | C19: =Assumptions!$B$5*Assumptions!$B$11+Assumptions!$B$6*Assumptions!$B$12+Assumptions!$B$7*Assumptions!$B$13 | D19: =B19*C19 | E19: =B19*Assumptions!$B$18*Assumptions!$B$17 | F19: =D19-E19 | G19: =Assumptions!$B$28+Assumptions!$B$29+Assumptions!$B$30+Assumptions!$B$31 | H19: =Assumptions!$B$37 | I19: =Assumptions!$B$19+IF(B19>500,B19*0.4,0) | J19: =Assumptions!$B$38+Assumptions!$B$39+Assumptions!$B$40 | K19: =G19+H19+I19+J19 | L19: =F19-K19 | M19: =M18+L19 | N19: =D19*12
A20: M17 | B20: 210 | C20: =Assumptions!$B$5*Assumptions!$B$11+Assumptions!$B$6*Assumptions!$B$12+Assumptions!$B$7*Assumptions!$B$13 | D20: =B20*C20 | E20: =B20*Assumptions!$B$18*Assumptions!$B$17 | F20: =D20-E20 | G20: =Assumptions!$B$28+Assumptions!$B$29+Assumptions!$B$30+Assumptions!$B$31 | H20: =Assumptions!$B$37 | I20: =Assumptions!$B$19+IF(B20>500,B20*0.4,0) | J20: =Assumptions!$B$38+Assumptions!$B$39+Assumptions!$B$40 | K20: =G20+H20+I20+J20 | L20: =F20-K20 | M20: =M19+L20 | N20: =D20*12
A21: M18 | B21: 250 | C21: =Assumptions!$B$5*Assumptions!$B$11+Assumptions!$B$6*Assumptions!$B$12+Assumptions!$B$7*Assumptions!$B$13 | D21: =B21*C21 | E21: =B21*Assumptions!$B$18*Assumptions!$B$17 | F21: =D21-E21 | G21: =Assumptions!$B$28+Assumptions!$B$29+Assumptions!$B$30+Assumptions!$B$31+Assumptions!$B$32 | H21: =Assumptions!$B$37 | I21: =Assumptions!$B$19+IF(B21>500,B21*0.4,0) | J21: =Assumptions!$B$38+Assumptions!$B$39+Assumptions!$B$40 | K21: =G21+H21+I21+J21 | L21: =F21-K21 | M21: =M20+L21 | N21: =D21*12
A22: M19 | B22: 290 | C22: =Assumptions!$B$5*Assumptions!$B$11+Assumptions!$B$6*Assumptions!$B$12+Assumptions!$B$7*Assumptions!$B$13 | D22: =B22*C22 | E22: =B22*Assumptions!$B$18*Assumptions!$B$17 | F22: =D22-E22 | G22: =Assumptions!$B$28+Assumptions!$B$29+Assumptions!$B$30+Assumptions!$B$31+Assumptions!$B$32 | H22: =Assumptions!$B$37 | I22: =Assumptions!$B$19+IF(B22>500,B22*0.4,0) | J22: =Assumptions!$B$38+Assumptions!$B$39+Assumptions!$B$40 | K22: =G22+H22+I22+J22 | L22: =F22-K22 | M22: =M21+L22 | N22: =D22*12
A23: M20 | B23: 335 | C23: =Assumptions!$B$5*Assumptions!$B$11+Assumptions!$B$6*Assumptions!$B$12+Assumptions!$B$7*Assumptions!$B$13 | D23: =B23*C23 | E23: =B23*Assumptions!$B$18*Assumptions!$B$17 | F23: =D23-E23 | G23: =Assumptions!$B$28+Assumptions!$B$29+Assumptions!$B$30+Assumptions!$B$31+Assumptions!$B$32 | H23: =Assumptions!$B$37 | I23: =Assumptions!$B$19+IF(B23>500,B23*0.4,0) | J23: =Assumptions!$B$38+Assumptions!$B$39+Assumptions!$B$40 | K23: =G23+H23+I23+J23 | L23: =F23-K23 | M23: =M22+L23 | N23: =D23*12
A24: M21 | B24: 380 | C24: =Assumptions!$B$5*Assumptions!$B$11+Assumptions!$B$6*Assumptions!$B$12+Assumptions!$B$7*Assumptions!$B$13 | D24: =B24*C24 | E24: =B24*Assumptions!$B$18*Assumptions!$B$17 | F24: =D24-E24 | G24: =Assumptions!$B$28+Assumptions!$B$29+Assumptions!$B$30+Assumptions!$B$31+Assumptions!$B$32 | H24: =Assumptions!$B$37 | I24: =Assumptions!$B$19+IF(B24>500,B24*0.4,0) | J24: =Assumptions!$B$38+Assumptions!$B$39+Assumptions!$B$40 | K24: =G24+H24+I24+J24 | L24: =F24-K24 | M24: =M23+L24 | N24: =D24*12
A25: M22 | B25: 425 | C25: =Assumptions!$B$5*Assumptions!$B$11+Assumptions!$B$6*Assumptions!$B$12+Assumptions!$B$7*Assumptions!$B$13 | D25: =B25*C25 | E25: =B25*Assumptions!$B$18*Assumptions!$B$17 | F25: =D25-E25 | G25: =Assumptions!$B$28+Assumptions!$B$29+Assumptions!$B$30+Assumptions!$B$31+Assumptions!$B$32 | H25: =Assumptions!$B$37 | I25: =Assumptions!$B$19+IF(B25>500,B25*0.4,0) | J25: =Assumptions!$B$38+Assumptions!$B$39+Assumptions!$B$40 | K25: =G25+H25+I25+J25 | L25: =F25-K25 | M25: =M24+L25 | N25: =D25*12
A26: M23 | B26: 460 | C26: =Assumptions!$B$5*Assumptions!$B$11+Assumptions!$B$6*Assumptions!$B$12+Assumptions!$B$7*Assumptions!$B$13 | D26: =B26*C26 | E26: =B26*Assumptions!$B$18*Assumptions!$B$17 | F26: =D26-E26 | G26: =Assumptions!$B$28+Assumptions!$B$29+Assumptions!$B$30+Assumptions!$B$31+Assumptions!$B$32 | H26: =Assumptions!$B$37 | I26: =Assumptions!$B$19+IF(B26>500,B26*0.4,0) | J26: =Assumptions!$B$38+Assumptions!$B$39+Assumptions!$B$40 | K26: =G26+H26+I26+J26 | L26: =F26-K26 | M26: =M25+L26 | N26: =D26*12
A27: M24 | B27: 500 | C27: =Assumptions!$B$5*Assumptions!$B$11+Assumptions!$B$6*Assumptions!$B$12+Assumptions!$B$7*Assumptions!$B$13 | D27: =B27*C27 | E27: =B27*Assumptions!$B$18*Assumptions!$B$17 | F27: =D27-E27 | G27: =Assumptions!$B$28+Assumptions!$B$29+Assumptions!$B$30+Assumptions!$B$31+Assumptions!$B$32+Assumptions!$B$33 | H27: =Assumptions!$B$37 | I27: =Assumptions!$B$19+IF(B27>500,B27*0.4,0) | J27: =Assumptions!$B$38+Assumptions!$B$39+Assumptions!$B$40 | K27: =G27+H27+I27+J27 | L27: =F27-K27 | M27: =M26+L27 | N27: =D27*12
A28: M25 | B28: 545 | C28: =Assumptions!$B$5*Assumptions!$B$11+Assumptions!$B$6*Assumptions!$B$12+Assumptions!$B$7*Assumptions!$B$13 | D28: =B28*C28 | E28: =B28*Assumptions!$B$18*Assumptions!$B$17 | F28: =D28-E28 | G28: =Assumptions!$B$28+Assumptions!$B$29+Assumptions!$B$30+Assumptions!$B$31+Assumptions!$B$32+Assumptions!$B$33 | H28: =Assumptions!$B$37 | I28: =Assumptions!$B$19+IF(B28>500,B28*0.4,0) | J28: =Assumptions!$B$38+Assumptions!$B$39+Assumptions!$B$40 | K28: =G28+H28+I28+J28 | L28: =F28-K28 | M28: =M27+L28 | N28: =D28*12
A29: M26 | B29: 605 | C29: =Assumptions!$B$5*Assumptions!$B$11+Assumptions!$B$6*Assumptions!$B$12+Assumptions!$B$7*Assumptions!$B$13 | D29: =B29*C29 | E29: =B29*Assumptions!$B$18*Assumptions!$B$17 | F29: =D29-E29 | G29: =Assumptions!$B$28+Assumptions!$B$29+Assumptions!$B$30+Assumptions!$B$31+Assumptions!$B$32+Assumptions!$B$33 | H29: =Assumptions!$B$37 | I29: =Assumptions!$B$19+IF(B29>500,B29*0.4,0) | J29: =Assumptions!$B$38+Assumptions!$B$39+Assumptions!$B$40 | K29: =G29+H29+I29+J29 | L29: =F29-K29 | M29: =M28+L29 | N29: =D29*12
A30: M27 | B30: 665 | C30: =Assumptions!$B$5*Assumptions!$B$11+Assumptions!$B$6*Assumptions!$B$12+Assumptions!$B$7*Assumptions!$B$13 | D30: =B30*C30 | E30: =B30*Assumptions!$B$18*Assumptions!$B$17 | F30: =D30-E30 | G30: =Assumptions!$B$28+Assumptions!$B$29+Assumptions!$B$30+Assumptions!$B$31+Assumptions!$B$32+Assumptions!$B$33 | H30: =Assumptions!$B$37 | I30: =Assumptions!$B$19+IF(B30>500,B30*0.4,0) | J30: =Assumptions!$B$38+Assumptions!$B$39+Assumptions!$B$40 | K30: =G30+H30+I30+J30 | L30: =F30-K30 | M30: =M29+L30 | N30: =D30*12
A31: M28 | B31: 725 | C31: =Assumptions!$B$5*Assumptions!$B$11+Assumptions!$B$6*Assumptions!$B$12+Assumptions!$B$7*Assumptions!$B$13 | D31: =B31*C31 | E31: =B31*Assumptions!$B$18*Assumptions!$B$17 | F31: =D31-E31 | G31: =Assumptions!$B$28+Assumptions!$B$29+Assumptions!$B$30+Assumptions!$B$31+Assumptions!$B$32+Assumptions!$B$33 | H31: =Assumptions!$B$37 | I31: =Assumptions!$B$19+IF(B31>500,B31*0.4,0) | J31: =Assumptions!$B$38+Assumptions!$B$39+Assumptions!$B$40 | K31: =G31+H31+I31+J31 | L31: =F31-K31 | M31: =M30+L31 | N31: =D31*12
A32: M29 | B32: 775 | C32: =Assumptions!$B$5*Assumptions!$B$11+Assumptions!$B$6*Assumptions!$B$12+Assumptions!$B$7*Assumptions!$B$13 | D32: =B32*C32 | E32: =B32*Assumptions!$B$18*Assumptions!$B$17 | F32: =D32-E32 | G32: =Assumptions!$B$28+Assumptions!$B$29+Assumptions!$B$30+Assumptions!$B$31+Assumptions!$B$32+Assumptions!$B$33 | H32: =Assumptions!$B$37 | I32: =Assumptions!$B$19+IF(B32>500,B32*0.4,0) | J32: =Assumptions!$B$38+Assumptions!$B$39+Assumptions!$B$40 | K32: =G32+H32+I32+J32 | L32: =F32-K32 | M32: =M31+L32 | N32: =D32*12
A33: M30 | B33: 800 | C33: =Assumptions!$B$5*Assumptions!$B$11+Assumptions!$B$6*Assumptions!$B$12+Assumptions!$B$7*Assumptions!$B$13 | D33: =B33*C33 | E33: =B33*Assumptions!$B$18*Assumptions!$B$17 | F33: =D33-E33 | G33: =Assumptions!$B$28+Assumptions!$B$29+Assumptions!$B$30+Assumptions!$B$31+Assumptions!$B$32+Assumptions!$B$33 | H33: =Assumptions!$B$37 | I33: =Assumptions!$B$19+IF(B33>500,B33*0.4,0) | J33: =Assumptions!$B$38+Assumptions!$B$39+Assumptions!$B$40 | K33: =G33+H33+I33+J33 | L33: =F33-K33 | M33: =M32+L33 | N33: =D33*12
A34: M31 | B34: 855 | C34: =Assumptions!$B$5*Assumptions!$B$11+Assumptions!$B$6*Assumptions!$B$12+Assumptions!$B$7*Assumptions!$B$13 | D34: =B34*C34 | E34: =B34*Assumptions!$B$18*Assumptions!$B$17 | F34: =D34-E34 | G34: =Assumptions!$B$28+Assumptions!$B$29+Assumptions!$B$30+Assumptions!$B$31+Assumptions!$B$32+Assumptions!$B$33 | H34: =Assumptions!$B$37 | I34: =Assumptions!$B$19+IF(B34>500,B34*0.4,0) | J34: =Assumptions!$B$38+Assumptions!$B$39+Assumptions!$B$40 | K34: =G34+H34+I34+J34 | L34: =F34-K34 | M34: =M33+L34 | N34: =D34*12
A35: M32 | B35: 915 | C35: =Assumptions!$B$5*Assumptions!$B$11+Assumptions!$B$6*Assumptions!$B$12+Assumptions!$B$7*Assumptions!$B$13 | D35: =B35*C35 | E35: =B35*Assumptions!$B$18*Assumptions!$B$17 | F35: =D35-E35 | G35: =Assumptions!$B$28+Assumptions!$B$29+Assumptions!$B$30+Assumptions!$B$31+Assumptions!$B$32+Assumptions!$B$33 | H35: =Assumptions!$B$37 | I35: =Assumptions!$B$19+IF(B35>500,B35*0.4,0) | J35: =Assumptions!$B$38+Assumptions!$B$39+Assumptions!$B$40 | K35: =G35+H35+I35+J35 | L35: =F35-K35 | M35: =M34+L35 | N35: =D35*12
A36: M33 | B36: 985 | C36: =Assumptions!$B$5*Assumptions!$B$11+Assumptions!$B$6*Assumptions!$B$12+Assumptions!$B$7*Assumptions!$B$13 | D36: =B36*C36 | E36: =B36*Assumptions!$B$18*Assumptions!$B$17 | F36: =D36-E36 | G36: =Assumptions!$B$28+Assumptions!$B$29+Assumptions!$B$30+Assumptions!$B$31+Assumptions!$B$32+Assumptions!$B$33 | H36: =Assumptions!$B$37 | I36: =Assumptions!$B$19+IF(B36>500,B36*0.4,0) | J36: =Assumptions!$B$38+Assumptions!$B$39+Assumptions!$B$40 | K36: =G36+H36+I36+J36 | L36: =F36-K36 | M36: =M35+L36 | N36: =D36*12
A37: M34 | B37: 1060 | C37: =Assumptions!$B$5*Assumptions!$B$11+Assumptions!$B$6*Assumptions!$B$12+Assumptions!$B$7*Assumptions!$B$13 | D37: =B37*C37 | E37: =B37*Assumptions!$B$18*Assumptions!$B$17 | F37: =D37-E37 | G37: =Assumptions!$B$28+Assumptions!$B$29+Assumptions!$B$30+Assumptions!$B$31+Assumptions!$B$32+Assumptions!$B$33 | H37: =Assumptions!$B$37 | I37: =Assumptions!$B$19+IF(B37>500,B37*0.4,0) | J37: =Assumptions!$B$38+Assumptions!$B$39+Assumptions!$B$40 | K37: =G37+H37+I37+J37 | L37: =F37-K37 | M37: =M36+L37 | N37: =D37*12
A38: M35 | B38: 1130 | C38: =Assumptions!$B$5*Assumptions!$B$11+Assumptions!$B$6*Assumptions!$B$12+Assumptions!$B$7*Assumptions!$B$13 | D38: =B38*C38 | E38: =B38*Assumptions!$B$18*Assumptions!$B$17 | F38: =D38-E38 | G38: =Assumptions!$B$28+Assumptions!$B$29+Assumptions!$B$30+Assumptions!$B$31+Assumptions!$B$32+Assumptions!$B$33 | H38: =Assumptions!$B$37 | I38: =Assumptions!$B$19+IF(B38>500,B38*0.4,0) | J38: =Assumptions!$B$38+Assumptions!$B$39+Assumptions!$B$40 | K38: =G38+H38+I38+J38 | L38: =F38-K38 | M38: =M37+L38 | N38: =D38*12
A39: M36 | B39: 1200 | C39: =Assumptions!$B$5*Assumptions!$B$11+Assumptions!$B$6*Assumptions!$B$12+Assumptions!$B$7*Assumptions!$B$13 | D39: =B39*C39 | E39: =B39*Assumptions!$B$18*Assumptions!$B$17 | F39: =D39-E39 | G39: =Assumptions!$B$28+Assumptions!$B$29+Assumptions!$B$30+Assumptions!$B$31+Assumptions!$B$32+Assumptions!$B$33 | H39: =Assumptions!$B$37 | I39: =Assumptions!$B$19+IF(B39>500,B39*0.4,0) | J39: =Assumptions!$B$38+Assumptions!$B$39+Assumptions!$B$40 | K39: =G39+H39+I39+J39 | L39: =F39-K39 | M39: =M38+L39 | N39: =D39*12

Sheet Charts
A1: Visuals

Sheet Use of funds
A1: Use of funds — $400K seed
A3: Bucket | B3: Amount (USD) | C3: % of round
A4: Engineering (1 senior eng × 18 months + founder) | B4: 160000 | C4: 0.4
A5: Merchant operations (hiring + onboarding first 100) | B5: 100000 | C5: 0.25
A6: Marketing (paid + content + events) | B6: 60000 | C6: 0.15
A7: Infrastructure (LLM tokens, hosting, scaling) | B7: 60000 | C7: 0.15
A8: Buffer (legal, contingencies) | B8: 20000 | C8: 0.05
A10: TOTAL | B10: =SUM(B4:B8) | C10: =SUM(C4:C8)
